Metadata-Version: 2.1
Name: classGenerator
Version: 0.0.2
Summary: Generador de clases en python
Home-page: https://github.com/DanielDubonDR/CreateClasses.git
Author: Daniel Dubon Rodriguez
Author-email: danieldubon499@gmail.com
License: MIT
Keywords: class,object,createClass,generateClass,generatorClass
Platform: UNKNOWN
Classifier: Development Status :: 4 - Beta
Classifier: Intended Audience :: Developers
Classifier: Topic :: Software Development :: Build Tools
Classifier: Programming Language :: Python :: 2.7
Classifier: Programming Language :: Python :: 3.4
Classifier: Programming Language :: Python :: 3.5
Classifier: Programming Language :: Python :: 3.6
Classifier: Programming Language :: Python :: 3.7
